pynonymizer/__init__.py
pynonymizer/__main__.py
pynonymizer/cli.py
pynonymizer/exceptions.py
pynonymizer/process_steps.py
pynonymizer/pynonymize.py
pynonymizer/database/__init__.py
pynonymizer/database/exceptions.py
pynonymizer/database/io.py
pynonymizer/database/provider.py
pynonymizer/database/mssql/__init__.py
pynonymizer/database/mssql/connectionstring.py
pynonymizer/database/mysql/__init__.py
pynonymizer/database/mysql/execution.py
pynonymizer/database/mysql/query_factory.py
pynonymizer/database/postgres/__init__.py
pynonymizer/database/postgres/execution.py
pynonymizer/database/postgres/query_factory.py
pynonymizer/fake/__init__.py
pynonymizer/strategy/__init__.py
pynonymizer/strategy/config.py
pynonymizer/strategy/database.py
pynonymizer/strategy/exceptions.py
pynonymizer/strategy/parser.py
pynonymizer/strategy/table.py
pynonymizer/strategy/update_column.py
pynonymizer-2.5.0.dist-info/LICENSE
pynonymizer-2.5.0.dist-info/METADATA
pynonymizer-2.5.0.dist-info/WHEEL
pynonymizer-2.5.0.dist-info/entry_points.txt
pynonymizer-2.5.0.dist-info/top_level.txt
pynonymizer-2.5.0.dist-info/RECORD
