Metadata-Version: 2.1
Name: pynonymizer
Version: 2.5.0
Summary: An anonymization tool for production databases
Home-page: https://github.com/rwnx/pynonymizer
Author: Rowan Twell
Author-email: rowantwell@gmail.com
License: MIT
Keywords: anonymization gdpr database mysql
Classifier: Development Status :: 5 - Production/Stable
Classifier: License :: OSI Approved :: MIT License
Classifier: Operating System :: MacOS :: MacOS X
Classifier: Operating System :: Microsoft :: Windows
Classifier: Operating System :: POSIX
Classifier: Topic :: Database
Classifier: Intended Audience :: Developers
Requires-Python: >3.9.0
License-File: LICENSE
Requires-Dist: pyyaml>=5
Requires-Dist: tqdm>=4
Requires-Dist: faker>=1
Requires-Dist: typer[all]>=0.9.0
Provides-Extra: mssql
Requires-Dist: pyodbc>=4.0.26; extra == "mssql"
